erudite
