Metadata-Version: 1.0
Name: Erudite
Version: 1.1.0
Summary: Log your command history to an analytics engine
Home-page: https://github.com/BrianHicks/erudite
Author: Brian Hicks
Author-email: brian@brianthicks.com
License: Apache 2.0
Download-URL: https://github.com/BrianHicks/erudite
Platform: UNKNOWN
Classifier: Development Status :: 3 - Alpha
Classifier: Environment :: Console
Classifier: Natural Language :: English
Classifier: Programming Language :: Python :: 2.7
Classifier: Topic :: Utilities
